akasaka/__init__.py
akasaka/executor.py
akasaka/loader.py
akasaka/main.py
akasaka/task.py
akasaka/torch_executor.py
akasaka/torch_single_executor.py
akasaka/torch_task.py
akasaka/utils/__init__.py
akasaka/utils/helper.py
akasaka/utils/io.py
akasaka-0.1.6.dist-info/LICENSE
akasaka-0.1.6.dist-info/METADATA
akasaka-0.1.6.dist-info/WHEEL
akasaka-0.1.6.dist-info/entry_points.txt
akasaka-0.1.6.dist-info/top_level.txt
akasaka-0.1.6.dist-info/RECORD
