Metadata-Version: 2.1
Name: akasaka
Version: 0.1.6
Summary: Dynamic mutiprocess preprocessing task loader and dispatcher
Home-page: https://github.com/JeffersonQin/akasaka
Author: Haoyun Qin
Author-email: qhy.cis@gmail.com
Classifier: Programming Language :: Python :: 3
Classifier: License :: OSI Approved :: MIT License
Classifier: Operating System :: OS Independent
Requires-Python: >=3.6
License-File: LICENSE
Requires-Dist: tqdm
